langchain_llamacpp_chat_model/__init__.py
langchain_llamacpp_chat_model/llama_chat_model.py
langchain_llamacpp_chat_model/llama_client_async_proxy.py
langchain_llamacpp_chat_model/llama_client_proxy.py
langchain_llamacpp_chat_model/proxy/__init__.py
langchain_llamacpp_chat_model/proxy/llama_proxy_chat_model.py
langchain_llamacpp_chat_model-0.2.2.dist-info/METADATA
langchain_llamacpp_chat_model-0.2.2.dist-info/WHEEL
langchain_llamacpp_chat_model-0.2.2.dist-info/RECORD
