Metadata-Version: 2.1
Name: langchain-llamacpp-chat-model
Version: 0.2.2
Summary: 
License: MIT
Requires-Python: >=3.9,<4.0
Classifier: License :: OSI Approved :: MIT License
Classifier: Programming Language :: Python :: 3
Classifier: Programming Language :: Python :: 3.9
Classifier: Programming Language :: Python :: 3.10
Classifier: Programming Language :: Python :: 3.11
Classifier: Programming Language :: Python :: 3.12
Provides-Extra: langchain
Provides-Extra: llama-proxy
Requires-Dist: anyio (>=4.4.0,<5.0.0) ; extra == "llama-proxy"
Requires-Dist: fastapi (>=0.111.0,<0.112.0) ; extra == "llama-proxy"
Requires-Dist: langchain (>=0.2.6,<0.3.0) ; extra == "langchain"
Requires-Dist: langchain-openai (>=0.1.14,<0.2.0)
Requires-Dist: llama-cpp-python (>=0.2.81,<0.3.0)
Requires-Dist: pydantic-settings (>=2.3.4,<3.0.0)
Requires-Dist: sse-starlette (>=2.1.2,<3.0.0) ; extra == "llama-proxy"
Requires-Dist: starlette-context (>=0.3.6,<0.4.0) ; extra == "llama-proxy"
